apollo/__init__.py
apollo/__main__.py
apollo/apollo.py
apollo/arguments.py
apollo/custom_checker.py
apollo/diff_checker.py
apollo/epsilon_checker.py
apollo/token_checker.py
apollo/verdict.py
apollo_tylerhm-0.1.0.dist-info/LICENSE
apollo_tylerhm-0.1.0.dist-info/METADATA
apollo_tylerhm-0.1.0.dist-info/WHEEL
apollo_tylerhm-0.1.0.dist-info/entry_points.txt
apollo_tylerhm-0.1.0.dist-info/top_level.txt
apollo_tylerhm-0.1.0.dist-info/RECORD
